abstractcontext/__init__.py
abstractcontext-0.1.0.dist-info/licenses/LICENSE
abstractcontext-0.1.0.dist-info/METADATA
abstractcontext-0.1.0.dist-info/WHEEL
abstractcontext-0.1.0.dist-info/top_level.txt
abstractcontext-0.1.0.dist-info/RECORD
