Metadata-Version: 2.4
Name: abstractcontext
Version: 0.1.0
Summary: Redefining active token memory design for GenAI systems
Author-email: Laurent-Philippe Albou <contact@abstractcore.ai>
Maintainer-email: "AbstractCore.ai Team" <contact@abstractcore.ai>
License: MIT
Project-URL: Homepage, https://github.com/lpalbou/abstractcore
Project-URL: Documentation, https://abstractcore.ai/docs
Project-URL: Repository, https://github.com/lpalbou/abstractcore
Project-URL: Bug Tracker, https://github.com/lpalbou/abstractcore/issues
Project-URL: Organization, https://abstractcore.ai
Keywords: ai,genai,memory,context,tokens,llm
Classifier: Development Status :: 2 - Pre-Alpha
Classifier: Intended Audience :: Developers
Classifier: Intended Audience :: Science/Research
Classifier: License :: OSI Approved :: MIT License
Classifier: Operating System :: OS Independent
Classifier: Programming Language :: Python :: 3
Classifier: Programming Language :: Python :: 3.8
Classifier: Programming Language :: Python :: 3.9
Classifier: Programming Language :: Python :: 3.10
Classifier: Programming Language :: Python :: 3.11
Classifier: Programming Language :: Python :: 3.12
Classifier: Topic :: Scientific/Engineering :: Artificial Intelligence
Classifier: Topic :: Software Development :: Libraries :: Python Modules
Requires-Python: >=3.8
License-File: LICENSE
Provides-Extra: dev
Requires-Dist: pytest>=7.0; extra == "dev"
Requires-Dist: pytest-cov>=4.0; extra == "dev"
Requires-Dist: black>=23.0; extra == "dev"
Requires-Dist: isort>=5.0; extra == "dev"
Requires-Dist: flake8>=6.0; extra == "dev"
Requires-Dist: mypy>=1.0; extra == "dev"
Dynamic: license-file
